sram_2port_bank/sram_array.sv
module sram_array(
    output reg [15:0] outA,
    output reg [15:0] outB,
    input [31:0] wordA,
    input [31:0] wordB,
    input ReadEn,
    input WriteEn,
    input [15:0] in,
    input srclkneg,
    input srclkpos
);


reg flag = 1;
reg [15:0] sram [0:31]; // sram array




//initialize all the sram addresses to 0.
always @(srclkneg) begin
    if (flag) begin
        sram[0] = 16'h0000;
        sram[1] = 16'h0000;
        sram[2] = 16'h0000;
        sram[3] = 16'h0000;
        sram[4] = 16'h0000;
        sram[5] = 16'h0000;
        sram[6] = 16'h0000;
        sram[7] = 16'h0000;
        sram[8] = 16'h0000;
        sram[9] = 16'h0000;
        sram[10] = 16'h0000;
        sram[11] = 16'h0000;
        sram[12] = 16'h0000;
        sram[13] = 16'h0000;
        sram[14] = 16'h0000;
        sram[15] = 16'h0000;
        sram[16] = 16'h0000;
        sram[17] = 16'h0000;
        sram[18] = 16'h0000;
        sram[19] = 16'h0000;
        sram[20] = 16'h0000;
        sram[21] = 16'h0000;
        sram[22] = 16'h0000;
        sram[23] = 16'h0000;
        sram[24] = 16'h0000;
        sram[25] = 16'h0000;
        sram[26] = 16'h0000;
        sram[27] = 16'h0000;
        sram[28] = 16'h0000;
        sram[29] = 16'h0000;
        sram[30] = 16'h0000;
        sram[31] = 16'h0000;
        flag = 0;
    end
end

reg [4:0] convA; // used to convert 1hot to index
reg [4:0] convB; // used to convert 1hot to index
// we will loop through the 32 bits of wordA and wordB, if it is high we will set conv to that index
integer i;

always @(*) begin
    convA = 5'b00000;
    convB = 5'b00000;
    for (i = 1; i < 31; i = i + 1) begin
        if (wordA[i]) begin
            convA = i[4:0];
        end
        if (wordB[i]) begin
            convB = i[4:0];
        end
    end
end

always @(posedge ReadEn || WriteEn) begin
    // writing to SRAM 
     
    if (ReadEn) begin
        outA = sram[convA];
        outB = sram[convB];
    end

    if(WriteEn) begin
        sram[0] <= 16'h0000;
        sram[convA] <= in;
        sram[convB] <= in;
    end
end

endmodule

bennettclock/bennettClock.sv
module bennett_clock #(
    parameter integer PHASES = 4
) (
    input wire clk,
    input wire reset,
    output reg [PHASES-1:0] clkp,
    output reg Mclk,
    output reg instFlag
);

    // The total number of states in the sequence is 2*PHASES + 2
    localparam MAX_STATE = 2 * PHASES + 1;
    // Calculate the required width for the state register.
    localparam STATE_WIDTH = $clog2(MAX_STATE + 1);

    reg [STATE_WIDTH-1:0] state;
  
	// To generate Mclk
    always @(posedge clk) begin
      if (clkp[PHASES-2] == 1) begin
        Mclk <= 1;
      end else if (instFlag ==1) begin
        Mclk <= 0;
      end

    end
 
    always @(posedge clk or posedge reset) begin
        if (reset) begin
            // On reset, initialize the state to 0.
            state <= 0;
        end else begin
            // Cycle through the states up to the calculated maximum.
            if (state == MAX_STATE)
                state <= 0;
            else
                state <= state + 1;
        end
    end
 						
    always @(*) begin
        integer i;
        // instFlag should only be high for one cycle when state is 0.
        // Set its default value to low.
        instFlag = 1'b0;
        if (state == 0) begin
            // State 0: All phases are low.
            clkp = '0;
            // Pulse the instruction flag high during this state.
            instFlag = 1'b1;
        end else if (state <= PHASES) begin
            // States 1 to PHASES: Rising edge sequence.
            for (i = 0; i < PHASES; i = i + 1) begin
                if (i < state - 1)
                    clkp[i] = 1'b1;
                else if (i == state - 1)
                    clkp[i] = 1'bx;
                else
                    clkp[i] = 1'b0;
            end
        end else if (state == PHASES + 1) begin
            // State (PHASES + 1): All phases are high.
            clkp = '1;
        end else begin // state > PHASES + 1
            // States (PHASES + 2) to MAX_STATE: Falling edge sequence.
            for (i = 0; i < PHASES; i = i + 1) begin
                 // Calculate the current step in the falling sequence.
                if (i < (MAX_STATE - state))
                    clkp[i] = 1'b1;
                else if (i == (MAX_STATE - state))
                    clkp[i] = 1'bx;
                else
                    clkp[i] = 1'b0;
            end
        end
    end

endmodule

tb/sram_2port_bank/sram_array_tb.sv

`include "../../bennettclock/bennettClock.sv"

module sram_array_tb();
// Parameters
localparam WIDTH = 16;
localparam ADDR_WIDTH = 32;

// Inputs
reg clk;
reg reset;
reg [ADDR_WIDTH-1:0] wordA;
reg [ADDR_WIDTH-1:0] wordB;
reg ReadEn;
reg WriteEn;
reg [WIDTH-1:0] in;
wire srclkneg;
wire srclkpos;
reg Mclk;
reg instFlag;

// Outputs
wire [WIDTH-1:0] outA;
wire [WIDTH-1:0] outB;
wire [9:0] clkpos;

bennett_clock #(
    .PHASES(10)
) bennett (
    .clk(clk),
    .reset(reset),
    .clkp(clkpos),
    .Mclk(Mclk),
    .instFlag(instFlag)
);

sram_array dut(
    outA, outB, wordA, wordB, ReadEn, WriteEn, in, srclkneg, srclkpos
);
// sram clock generation
// srclk transitins to null after phase 7. Returns to HiLo within the middle of the last bennett clk.
assign srclkneg = (Mclk ^ clkpos[6]) & clkpos[6];
assign srclkpos = ~srclkneg;

// wave dump
initial begin
    $dumpfile("sram_array.vcd");
    $dumpvars(0, sram_array_tb);
end

// Clock generation
initial begin
    clk = 0;
    forever #5 clk = ~clk;
end

// some notes, read enable arrives on ph7, write enable arrives on ph9
// address arrives on ph3
// data inputs arrive at ph5


// testbench notes:
// 12/27/25 Debug statements. Super weird continuity thing with SRAM on testbench peek vs waveform output.
// The waveform says that outA at wordA = 1, AKA address 1, is AAAA, which is correct.
// but the peek says AAAA actually appears at address 0 for some reason....
// probably something wrong on my for loop side?
reg [4:0] i;
initial begin
    reset = 1;
    #10;
    reset = 0;
    ReadEn = 0;
    WriteEn = 0;

    // Pre operation display all sram cell data
    $display("Pre Test peek into SRAM cells");
    for ( i = 0; i < 31; i = i + 1) begin
        $display("SRAM at address: %b --- Data: %b", i, dut.sram[i]);
    end
    $display("------ End of peek ------\n");

    $display("Begin Test Sequences --------------------------------\n");
    // Write operation
    @(posedge clkpos[2]);
    wordA = 32'b00000000000000000000000000000010;   // actaully the 1 address, because 1 hot!!!, 000.00001 is 0 address
    wordB = 32'b00000000000000000000000000000010;
    @(posedge clkpos[4]);
    in = 16'b1010101010101010;
    @(posedge clkpos[8]);
    WriteEn = 1;
    $display("Writing %b to address A: %h and address B: %h", in, wordA, wordB);
    @(posedge clkpos[9]);
    WriteEn = 0;
    $display("SRAM CELL address A: %h address B: %h\n Data: %b\n", wordA, wordB ,dut.sram[1]);

    // Write operation
    @(posedge clkpos[2]);
    wordA = 32'b00000000000000000000000000000100;       
    wordB = 32'b00000000000000000000000000000100;
    @(posedge clkpos[4]);
    in = 16'hABCD;
    @(posedge clkpos[8]);
    WriteEn = 1;
    $display("Writing %b to address A: %h and address B: %h", in, wordA, wordB);
    @(posedge clkpos[9]);
    WriteEn = 0;
    $display("SRAM CELL address A: %h address B: %h\n Data: %b\n", wordA, wordB ,dut.sram[2]);
   
    // Read operation
    @(posedge clkpos[2]);
    wordA = 32'b00000000000000000000000000000001;       
    wordB = 32'b00000000000000000000000000000010;
    @(posedge clkpos[6]);
    ReadEn = 1;
    $display("Reading from address A: %h --- Data: %b\n", wordA, dut.sram[0]);
    $display("Reading from address B: %h --- Data: %b\n", wordB, dut.sram[1]);
    @(posedge clkpos[8]);
    ReadEn = 0;
    $display("End of Test Sequences-----------------------------\n");

    // End of operation display all sram cell data
    $display("End of Test peek into SRAM cells");
    for ( i = 0; i < 31; i = i + 1) begin
        $display("SRAM at address: %b --- Data: %b", i, dut.sram[i]);
    end
    $display("------ End of peek ------\n");
    #400

    $finish;

end
endmodule

tb/sram_2port_bank/sram_array.vcd
$date
	Sat Dec 27 19:32:10 2025
$end
$version
	Icarus Verilog
$end
$timescale
	1s
$end
$scope module sram_array_tb $end
$var wire 1 ! srclkneg $end
$var wire 1 " srclkpos $end
$var wire 16 # outB [15:0] $end
$var wire 16 $ outA [15:0] $end
$var wire 1 % instFlag $end
$var wire 10 & clkpos [9:0] $end
$var wire 1 ' Mclk $end
$var parameter 32 ( ADDR_WIDTH $end
$var parameter 32 ) WIDTH $end
$var reg 1 * ReadEn $end
$var reg 1 + WriteEn $end
$var reg 1 , clk $end
$var reg 5 - i [4:0] $end
$var reg 16 . in [15:0] $end
$var reg 1 / reset $end
$var reg 32 0 wordA [31:0] $end
$var reg 32 1 wordB [31:0] $end
$scope module bennett $end
$var wire 1 , clk $end
$var wire 1 / reset $end
$var parameter 65 2 MAX_STATE $end
$var parameter 32 3 PHASES $end
$var parameter 32 4 STATE_WIDTH $end
$var reg 1 ' Mclk $end
$var reg 10 5 clkp [9:0] $end
$var reg 1 % instFlag $end
$var reg 5 6 state [4:0] $end
$scope begin $unm_blk_16 $end
$var integer 32 7 i [31:0] $end
$upscope $end
$upscope $end
$scope module dut $end
$var wire 1 * ReadEn $end
$var wire 1 + WriteEn $end
$var wire 16 8 in [15:0] $end
$var wire 1 ! srclkneg $end
$var wire 1 " srclkpos $end
$var wire 32 9 wordA [31:0] $end
$var wire 32 : wordB [31:0] $end
$var reg 5 ; convA [4:0] $end
$var reg 5 < convB [4:0] $end
$var reg 1 = flag $end
$var reg 16 > outA [15:0] $end
$var reg 16 ? outB [15:0] $end
$var integer 32 @ i [31:0] $end
$upscope $end
$upscope $end
$enddefinitions $end
$comment Show the parameter values. $end
$dumpall
b101 4
b1010 3
b10101 2
b10000 )
b100000 (
$end
#0
$dumpvars
bx @
bx ?
bx >
0=
bx <
bx ;
bx :
bx 9
bx 8
bx 7
b0 6
b0 5
bx 1
bx 0
1/
bx .
bx -
0,
x+
x*
x'
b0 &
1%
bx $
bx #
1"
0!
$end
#5
0'
1,
#10
0,
b11111 -
0+
0*
0/
#15
b0x &
b0x 5
b1010 7
0%
b1 6
1,
#20
0,
#25
b0x1 &
b0x1 5
b1010 7
b10 6
1,
#30
0,
#35
b11111 @
b1 <
b1 ;
b10 1
b10 :
b10 0
b10 9
b0x11 &
b0x11 5
b1010 7
b11 6
1,
#40
0,
#45
b0x111 &
b0x111 5
b1010 7
b100 6
1,
#50
0,
#55
b1010101010101010 .
b1010101010101010 8
b0x1111 &
b0x1111 5
b1010 7
b101 6
1,
#60
0,
#65
b0x11111 &
b0x11111 5
b1010 7
b110 6
1,
#70
0,
#75
x"
x!
b0x111111 &
b0x111111 5
b1010 7
b111 6
1,
#80
0,
#85
0"
1!
b0x1111111 &
b0x1111111 5
b1010 7
b1000 6
1,
#90
0,
#95
1+
b0x11111111 &
b0x11111111 5
b1010 7
b1001 6
1,
#100
0,
#105
0+
bx111111111 &
bx111111111 5
b1010 7
b1010 6
1,
#110
0,
#115
1"
0!
b1111111111 &
b1111111111 5
b1011 6
1'
1,
#120
0,
#125
bx111111111 &
bx111111111 5
b1010 7
b1100 6
1,
#130
0,
#135
b0x11111111 &
b0x11111111 5
b1010 7
b1101 6
1,
#140
0,
#145
b0x1111111 &
b0x1111111 5
b1010 7
b1110 6
1,
#150
0,
#155
x"
x!
b0x111111 &
b0x111111 5
b1010 7
b1111 6
1,
#160
0,
#165
1"
0!
b0x11111 &
b0x11111 5
b1010 7
b10000 6
1,
#170
0,
#175
b0x1111 &
b0x1111 5
b1010 7
b10001 6
1,
#180
0,
#185
b0x111 &
b0x111 5
b1010 7
b10010 6
1,
#190
0,
#195
b0x11 &
b0x11 5
b1010 7
b10011 6
1,
#200
0,
#205
b0x1 &
b0x1 5
b1010 7
b10100 6
1,
#210
0,
#215
b0x &
b0x 5
b1010 7
b10101 6
1,
#220
0,
#225
1%
b0 &
b0 5
b0 6
1,
#230
0,
#235
b0x &
b0x 5
b1010 7
0%
b1 6
0'
1,
#240
0,
#245
b0x1 &
b0x1 5
b1010 7
b10 6
1,
#250
0,
#255
b11111 @
b10 <
b10 ;
b100 1
b100 :
b100 0
b100 9
b0x11 &
b0x11 5
b1010 7
b11 6
1,
#260
0,
#265
b0x111 &
b0x111 5
b1010 7
b100 6
1,
#270
0,
#275
b1010101111001101 .
b1010101111001101 8
b0x1111 &
b0x1111 5
b1010 7
b101 6
1,
#280
0,
#285
b0x11111 &
b0x11111 5
b1010 7
b110 6
1,
#290
0,
#295
x"
x!
b0x111111 &
b0x111111 5
b1010 7
b111 6
1,
#300
0,
#305
0"
1!
b0x1111111 &
b0x1111111 5
b1010 7
b1000 6
1,
#310
0,
#315
1+
b0x11111111 &
b0x11111111 5
b1010 7
b1001 6
1,
#320
0,
#325
0+
bx111111111 &
bx111111111 5
b1010 7
b1010 6
1,
#330
0,
#335
1"
0!
b1111111111 &
b1111111111 5
b1011 6
1'
1,
#340
0,
#345
bx111111111 &
bx111111111 5
b1010 7
b1100 6
1,
#350
0,
#355
b0x11111111 &
b0x11111111 5
b1010 7
b1101 6
1,
#360
0,
#365
b0x1111111 &
b0x1111111 5
b1010 7
b1110 6
1,
#370
0,
#375
x"
x!
b0x111111 &
b0x111111 5
b1010 7
b1111 6
1,
#380
0,
#385
1"
0!
b0x11111 &
b0x11111 5
b1010 7
b10000 6
1,
#390
0,
#395
b0x1111 &
b0x1111 5
b1010 7
b10001 6
1,
#400
0,
#405
b0x111 &
b0x111 5
b1010 7
b10010 6
1,
#410
0,
#415
b0x11 &
b0x11 5
b1010 7
b10011 6
1,
#420
0,
#425
b0x1 &
b0x1 5
b1010 7
b10100 6
1,
#430
0,
#435
b0x &
b0x 5
b1010 7
b10101 6
1,
#440
0,
#445
1%
b0 &
b0 5
b0 6
1,
#450
0,
#455
b0x &
b0x 5
b1010 7
0%
b1 6
0'
1,
#460
0,
#465
b0x1 &
b0x1 5
b1010 7
b10 6
1,
#470
0,
#475
b11111 @
b1 <
b0 ;
b10 1
b10 :
b1 0
b1 9
b0x11 &
b0x11 5
b1010 7
b11 6
1,
#480
0,
#485
b0x111 &
b0x111 5
b1010 7
b100 6
1,
#490
0,
#495
b0x1111 &
b0x1111 5
b1010 7
b101 6
1,
#500
0,
#505
b0x11111 &
b0x11111 5
b1010 7
b110 6
1,
#510
0,
#515
b1010101010101010 #
b1010101010101010 ?
b0 $
b0 >
x"
1*
x!
b0x111111 &
b0x111111 5
b1010 7
b111 6
1,
#520
0,
#525
0"
1!
b0x1111111 &
b0x1111111 5
b1010 7
b1000 6
1,
#530
0,
#535
b11111 -
0*
b0x11111111 &
b0x11111111 5
b1010 7
b1001 6
1,
#540
0,
#545
bx111111111 &
bx111111111 5
b1010 7
b1010 6
1,
#550
0,
#555
1"
0!
b1111111111 &
b1111111111 5
b1011 6
1'
1,
#560
0,
#565
bx111111111 &
bx111111111 5
b1010 7
b1100 6
1,
#570
0,
#575
b0x11111111 &
b0x11111111 5
b1010 7
b1101 6
1,
#580
0,
#585
b0x1111111 &
b0x1111111 5
b1010 7
b1110 6
1,
#590
0,
#595
x"
x!
b0x111111 &
b0x111111 5
b1010 7
b1111 6
1,
#600
0,
#605
1"
0!
b0x11111 &
b0x11111 5
b1010 7
b10000 6
1,
#610
0,
#615
b0x1111 &
b0x1111 5
b1010 7
b10001 6
1,
#620
0,
#625
b0x111 &
b0x111 5
b1010 7
b10010 6
1,
#630
0,
#635
b0x11 &
b0x11 5
b1010 7
b10011 6
1,
#640
0,
#645
b0x1 &
b0x1 5
b1010 7
b10100 6
1,
#650
0,
#655
b0x &
b0x 5
b1010 7
b10101 6
1,
#660
0,
#665
1%
b0 &
b0 5
b0 6
1,
#670
0,
#675
b0x &
b0x 5
b1010 7
0%
b1 6
0'
1,
#680
0,
#685
b0x1 &
b0x1 5
b1010 7
b10 6
1,
#690
0,
#695
b0x11 &
b0x11 5
b1010 7
b11 6
1,
#700
0,
#705
b0x111 &
b0x111 5
b1010 7
b100 6
1,
#710
0,
#715
b0x1111 &
b0x1111 5
b1010 7
b101 6
1,
#720
0,
#725
b0x11111 &
b0x11111 5
b1010 7
b110 6
1,
#730
0,
#735
x"
x!
b0x111111 &
b0x111111 5
b1010 7
b111 6
1,
#740
0,
#745
0"
1!
b0x1111111 &
b0x1111111 5
b1010 7
b1000 6
1,
#750
0,
#755
b0x11111111 &
b0x11111111 5
b1010 7
b1001 6
1,
#760
0,
#765
bx111111111 &
bx111111111 5
b1010 7
b1010 6
1,
#770
0,
#775
1"
0!
b1111111111 &
b1111111111 5
b1011 6
1'
1,
#780
0,
#785
bx111111111 &
bx111111111 5
b1010 7
b1100 6
1,
#790
0,
#795
b0x11111111 &
b0x11111111 5
b1010 7
b1101 6
1,
#800
0,
#805
b0x1111111 &
b0x1111111 5
b1010 7
b1110 6
1,
#810
0,
#815
x"
x!
b0x111111 &
b0x111111 5
b1010 7
b1111 6
1,
#820
0,
#825
1"
0!
b0x11111 &
b0x11111 5
b1010 7
b10000 6
1,
#830
0,
#835
b0x1111 &
b0x1111 5
b1010 7
b10001 6
1,
#840
0,
#845
b0x111 &
b0x111 5
b1010 7
b10010 6
1,
#850
0,
#855
b0x11 &
b0x11 5
b1010 7
b10011 6
1,
#860
0,
#865
b0x1 &
b0x1 5
b1010 7
b10100 6
1,
#870
0,
#875
b0x &
b0x 5
b1010 7
b10101 6
1,
#880
0,
#885
1%
b0 &
b0 5
b0 6
1,
#890
0,
#895
b0x &
b0x 5
b1010 7
0%
b1 6
0'
1,
#900
0,
#905
b0x1 &
b0x1 5
b1010 7
b10 6
1,
#910
0,
#915
b0x11 &
b0x11 5
b1010 7
b11 6
1,
#920
0,
#925
b0x111 &
b0x111 5
b1010 7
b100 6
1,
#930
0,
#935
b0x1111 &
b0x1111 5
b1010 7
b101 6
1,
